neuralspot_edge/__init__.py
neuralspot_edge/callbacks/__init__.py
neuralspot_edge/callbacks/tqdm_progress_bar.py
neuralspot_edge/converters/__init__.py
neuralspot_edge/converters/cpp/__init__.py
neuralspot_edge/converters/cpp/utils.py
neuralspot_edge/converters/tflite/__init__.py
neuralspot_edge/converters/tflite/converter.py
neuralspot_edge/converters/torch/__init__.py
neuralspot_edge/interpreters/__init__.py
neuralspot_edge/interpreters/tflite/__init__.py
neuralspot_edge/interpreters/tflite/interpreter.py
neuralspot_edge/layers/__init__.py
neuralspot_edge/layers/activations.py
neuralspot_edge/layers/convolutional.py
neuralspot_edge/layers/mbconv.py
neuralspot_edge/layers/normalization.py
neuralspot_edge/layers/patching.py
neuralspot_edge/layers/preprocessing/__init__.py
neuralspot_edge/layers/preprocessing/amplitude_warp.py
neuralspot_edge/layers/preprocessing/augmentation_pipeline.py
neuralspot_edge/layers/preprocessing/base_augmentation.py
neuralspot_edge/layers/preprocessing/biquad_filter.py
neuralspot_edge/layers/preprocessing/defines.py
neuralspot_edge/layers/preprocessing/fir_filter.py
neuralspot_edge/layers/preprocessing/layer_normalization.py
neuralspot_edge/layers/preprocessing/random_augmentation_pipeline.py
neuralspot_edge/layers/preprocessing/random_background_noises.py
neuralspot_edge/layers/preprocessing/random_channel.py
neuralspot_edge/layers/preprocessing/random_choice.py
neuralspot_edge/layers/preprocessing/random_crop.py
neuralspot_edge/layers/preprocessing/random_cutout.py
neuralspot_edge/layers/preprocessing/random_flip.py
neuralspot_edge/layers/preprocessing/random_gaussian_noise.py
neuralspot_edge/layers/preprocessing/random_noise_distortion.py
neuralspot_edge/layers/preprocessing/random_sine_wave.py
neuralspot_edge/layers/preprocessing/rescaling.py
neuralspot_edge/layers/preprocessing/resizing.py
neuralspot_edge/layers/preprocessing/sine_wave.py
neuralspot_edge/layers/preprocessing/spec_augment.py
neuralspot_edge-0.2.2.dist-info/LICENSE
neuralspot_edge-0.2.2.dist-info/METADATA
neuralspot_edge-0.2.2.dist-info/WHEEL
neuralspot_edge-0.2.2.dist-info/RECORD
